sanic_session_sptk/__init__.py
sanic_session_sptk/plugin.py
Sanic_Session_SPTK-0.6.0.dist-info/LICENSE
Sanic_Session_SPTK-0.6.0.dist-info/METADATA
Sanic_Session_SPTK-0.6.0.dist-info/WHEEL
Sanic_Session_SPTK-0.6.0.dist-info/top_level.txt
Sanic_Session_SPTK-0.6.0.dist-info/RECORD
