Metadata-Version: 2.1
Name: Sanic-Session-SPTK
Version: 0.6.0
Summary: A SPF compatible distribution of Sanic-Session. Wraps upstream Sanic-Session.
Home-page: https://github.com/ashleysommer/sanic-session-sptk
Author: Ashley Sommer, Suby Raman
Author-email: ashleysommer@gmail.com
License: MIT
Platform: any
Classifier: Environment :: Web Environment
Classifier: Intended Audience :: Developers
Classifier: License :: OSI Approved :: MIT License
Classifier: Operating System :: OS Independent
Classifier: Programming Language :: Python
Classifier: Programming Language :: Python :: 3
Classifier: Programming Language :: Python :: 3 :: Only
Classifier: Programming Language :: Python :: Implementation :: CPython
Classifier: Programming Language :: Python :: Implementation :: PyPy
Classifier: Topic :: Internet :: WWW/HTTP :: Dynamic Content
Classifier: Topic :: Software Development :: Libraries :: Python Modules
License-File: LICENSE
Requires-Dist: sanic (<22,>=21.3.4)
Requires-Dist: sanic-plugin-toolkit (>=1.1.0.post1)
Requires-Dist: sanic-session
